gol_rand/__init__.py
gol_rand/grid_utils.py
gol_rand/random.py
gol_rand/utils.py
gol_rand-1.0.1.dist-info/METADATA
gol_rand-1.0.1.dist-info/RECORD
gol_rand-1.0.1.dist-info/WHEEL
gol_rand-1.0.1.dist-info/top_level.txt
